{
  "cross_domain_insights": [
    {
      "rule_id": "R001",
      "label": "vla-technique-cross",
      "source_domain": "vla",
      "target_domain": "ai_app",
      "title": "GraspLDP: Towards Generalizable Grasping Policy via Latent Diffusion",
      "url": "https://tldr.takara.ai/p/2602.22862",
      "rating": "🔧",
      "matched_keywords": [
        "diffusion"
      ],
      "abstract": "This paper focuses on enhancing the grasping precision and generalization of manipulation policies learned via imitation",
      "date": "2026-03-01"
    },
    {
      "date": "2026-03-03",
      "rule_id": "R003",
      "label": "aiapp-embodied-cross",
      "source_domain": "ai_app",
      "target_domain": "vla",
      "title": "Launch HN: OctaPulse (YC W26) – Robotics and computer vision for fish farming",
      "url": "https://news.ycombinator.com/item?id=47220320",
      "rating": "A",
      "matched_keywords": [
        "robot"
      ],
      "abstract": "Hi HN! My name is Rohan and, together with Paul, I’m the co-founder of OctaPulse ( https://www.tryoctapulse.com/ ). We’re building a robotics layer for seafood production, starting with automated fish",
      "score": 0.6,
      "recommendation_reason": "aiapp-embodied-cross: matched [robot] score=0.60"
    }
  ]
}